stats_confidence_intervals/__init__.py
stats_confidence_intervals/core.py
stats_confidence_intervals-0.2.3.dist-info/METADATA
stats_confidence_intervals-0.2.3.dist-info/WHEEL
stats_confidence_intervals-0.2.3.dist-info/top_level.txt
stats_confidence_intervals-0.2.3.dist-info/RECORD
