Metadata-Version: 2.4
Name: stats_confidence_intervals
Version: 0.2.3
Summary: A comprehensive library for calculating and visualizing statistical confidence intervals
Home-page: https://github.com/SubaashNair/Confidence-Interval-Library
Author: Subashanan Nair
Author-email: Subashanan Nair <subashanan.nair@gmail.com>
License: MIT
Project-URL: Homepage, https://github.com/SubaashNair/Confidence-Interval-Library
Project-URL: Repository, https://github.com/SubaashNair/Confidence-Interval-Library.git
Classifier: Development Status :: 4 - Beta
Classifier: Intended Audience :: Science/Research
Classifier: Intended Audience :: Education
Classifier: License :: OSI Approved :: MIT License
Classifier: Programming Language :: Python :: 3.7
Classifier: Programming Language :: Python :: 3.8
Classifier: Programming Language :: Python :: 3.9
Classifier: Programming Language :: Python :: 3.10
Classifier: Topic :: Scientific/Engineering
Classifier: Topic :: Software Development :: Libraries :: Python Modules
Requires-Python: >=3.7
Requires-Dist: numpy>=1.20.0
Requires-Dist: scipy>=1.7.0
Requires-Dist: matplotlib>=3.4.0
Dynamic: author
Dynamic: home-page
Dynamic: requires-python
